README.md
pyproject.toml
setup.py
obsln/__init__.py
obsln.egg-info/PKG-INFO
obsln.egg-info/SOURCES.txt
obsln.egg-info/dependency_links.txt
obsln.egg-info/entry_points.txt
obsln.egg-info/namespace_packages.txt
obsln.egg-info/not-zip-safe
obsln.egg-info/top_level.txt
obsln/core/__init__.py
obsln/core/compatibility.py
obsln/core/futureutils.py
obsln/core/stream.py
obsln/core/trace.py
obsln/core/utcdatetime.py
obsln/core/util/__init__.py
obsln/core/util/attribdict.py
obsln/core/util/base.py
obsln/core/util/decorator.py
obsln/core/util/libnames.py
obsln/core/util/misc.py
obsln/io/__init__.py
obsln/io/seg2/__init__.py
obsln/io/seg2/header.py
obsln/io/seg2/seg2.py
obsln/io/seg2/tests/__init__.py
obsln/io/seg2/tests/test_seg2.py
obsln/io/segy/__init__.py
obsln/io/segy/core.py
obsln/io/segy/header.py
obsln/io/segy/pack.py
obsln/io/segy/segy.py
obsln/io/segy/unpack.py
obsln/io/segy/util.py
obsln/io/segy/src/ibm2ieee.c
obsln/io/segy/tests/__init__.py
obsln/io/segy/tests/header.py
obsln/io/segy/tests/test_core.py
obsln/io/segy/tests/test_segy.py
obsln/io/segy/tests/test_su.py