Metadata-Version: 2.1
Name: obsln
Version: 0.0.8
Summary: A very limited range of functionality from ObsPy without many of the dependencies and size
Author: Bateared Collie
Author-email: BatearedCollie <batearedcolie@gmail.com>
Project-URL: Homepage, https://github.com/batearedcollie/obsln
Classifier: Programming Language :: Python :: 3
Classifier: License :: OSI Approved :: GNU Lesser General Public License v3 (LGPLv3)
Classifier: Operating System :: OS Independent
Requires-Python: >=3.10
